[
  {
    "station": "King's Park",
    "temp_c": 28,
    "humidity_pct": 82,
    "wet_bulb_temp_c": 25.52,
    "composite_risk_score": 4.0,
    "risk_level": "Safe",
    "recorded_at": "2026-07-08T10:08:48.553365+00:00"
  },
  {
    "station": "Hong Kong Observatory",
    "temp_c": 29,
    "humidity_pct": 82,
    "wet_bulb_temp_c": 26.47,
    "composite_risk_score": 4.0,
    "risk_level": "Safe",
    "recorded_at": "2026-07-08T10:08:48.553399+00:00"
  },
  {
    "station": "Wong Chuk Hang",
    "temp_c": 29,
    "humidity_pct": 82,
    "wet_bulb_temp_c": 26.47,
    "composite_risk_score": 4.0,
    "risk_level": "Safe",
    "recorded_at": "2026-07-08T10:08:48.553416+00:00"
  },
  {
    "station": "Ta Kwu Ling",
    "temp_c": 28,
    "humidity_pct": 82,
    "wet_bulb_temp_c": 25.52,
    "composite_risk_score": 4.0,
    "risk_level": "Safe",
    "recorded_at": "2026-07-08T10:08:48.553430+00:00"
  },
  {
    "station": "Lau Fau Shan",
    "temp_c": 27,
    "humidity_pct": 82,
    "wet_bulb_temp_c": 24.57,
    "composite_risk_score": 4.0,
    "risk_level": "Safe",
    "recorded_at": "2026-07-08T10:08:48.553443+00:00"
  },
  {
    "station": "Tai Po",
    "temp_c": 29,
    "humidity_pct": 82,
    "wet_bulb_temp_c": 26.47,
    "composite_risk_score": 4.0,
    "risk_level": "Safe",
    "recorded_at": "2026-07-08T10:08:48.553457+00:00"
  },
  {
    "station": "Sha Tin",
    "temp_c": 29,
    "humidity_pct": 82,
    "wet_bulb_temp_c": 26.47,
    "composite_risk_score": 4.0,
    "risk_level": "Safe",
    "recorded_at": "2026-07-08T10:08:48.553470+00:00"
  },
  {
    "station": "Tuen Mun",
    "temp_c": 27,
    "humidity_pct": 82,
    "wet_bulb_temp_c": 24.57,
    "composite_risk_score": 4.0,
    "risk_level": "Safe",
    "recorded_at": "2026-07-08T10:08:48.553482+00:00"
  },
  {
    "station": "Tseung Kwan O",
    "temp_c": 28,
    "humidity_pct": 82,
    "wet_bulb_temp_c": 25.52,
    "composite_risk_score": 4.0,
    "risk_level": "Safe",
    "recorded_at": "2026-07-08T10:08:48.553494+00:00"
  },
  {
    "station": "Sai Kung",
    "temp_c": 28,
    "humidity_pct": 82,
    "wet_bulb_temp_c": 25.52,
    "composite_risk_score": 4.0,
    "risk_level": "Safe",
    "recorded_at": "2026-07-08T10:08:48.553505+00:00"
  },
  {
    "station": "Cheung Chau",
    "temp_c": 27,
    "humidity_pct": 82,
    "wet_bulb_temp_c": 24.57,
    "composite_risk_score": 4.0,
    "risk_level": "Safe",
    "recorded_at": "2026-07-08T10:08:48.553534+00:00"
  },
  {
    "station": "Chek Lap Kok",
    "temp_c": 28,
    "humidity_pct": 82,
    "wet_bulb_temp_c": 25.52,
    "composite_risk_score": 4.0,
    "risk_level": "Safe",
    "recorded_at": "2026-07-08T10:08:48.553558+00:00"
  },
  {
    "station": "Tsing Yi",
    "temp_c": 29,
    "humidity_pct": 82,
    "wet_bulb_temp_c": 26.47,
    "composite_risk_score": 4.0,
    "risk_level": "Safe",
    "recorded_at": "2026-07-08T10:08:48.553579+00:00"
  },
  {
    "station": "Tsuen Wan Ho Koon",
    "temp_c": 27,
    "humidity_pct": 82,
    "wet_bulb_temp_c": 24.57,
    "composite_risk_score": 4.0,
    "risk_level": "Safe",
    "recorded_at": "2026-07-08T10:08:48.553599+00:00"
  },
  {
    "station": "Tsuen Wan Shing Mun Valley",
    "temp_c": 29,
    "humidity_pct": 82,
    "wet_bulb_temp_c": 26.47,
    "composite_risk_score": 4.0,
    "risk_level": "Safe",
    "recorded_at": "2026-07-08T10:08:48.553612+00:00"
  },
  {
    "station": "Hong Kong Park",
    "temp_c": 28,
    "humidity_pct": 82,
    "wet_bulb_temp_c": 25.52,
    "composite_risk_score": 4.0,
    "risk_level": "Safe",
    "recorded_at": "2026-07-08T10:08:48.553628+00:00"
  },
  {
    "station": "Shau Kei Wan",
    "temp_c": 28,
    "humidity_pct": 82,
    "wet_bulb_temp_c": 25.52,
    "composite_risk_score": 4.0,
    "risk_level": "Safe",
    "recorded_at": "2026-07-08T10:08:48.553640+00:00"
  },
  {
    "station": "Kowloon City",
    "temp_c": 29,
    "humidity_pct": 82,
    "wet_bulb_temp_c": 26.47,
    "composite_risk_score": 4.0,
    "risk_level": "Safe",
    "recorded_at": "2026-07-08T10:08:48.553652+00:00"
  },
  {
    "station": "Happy Valley",
    "temp_c": 29,
    "humidity_pct": 82,
    "wet_bulb_temp_c": 26.47,
    "composite_risk_score": 4.0,
    "risk_level": "Safe",
    "recorded_at": "2026-07-08T10:08:48.553663+00:00"
  },
  {
    "station": "Wong Tai Sin",
    "temp_c": 29,
    "humidity_pct": 82,
    "wet_bulb_temp_c": 26.47,
    "composite_risk_score": 4.0,
    "risk_level": "Safe",
    "recorded_at": "2026-07-08T10:08:48.553675+00:00"
  },
  {
    "station": "Stanley",
    "temp_c": 28,
    "humidity_pct": 82,
    "wet_bulb_temp_c": 25.52,
    "composite_risk_score": 4.0,
    "risk_level": "Safe",
    "recorded_at": "2026-07-08T10:08:48.553686+00:00"
  },
  {
    "station": "Kwun Tong",
    "temp_c": 29,
    "humidity_pct": 82,
    "wet_bulb_temp_c": 26.47,
    "composite_risk_score": 4.0,
    "risk_level": "Safe",
    "recorded_at": "2026-07-08T10:08:48.553698+00:00"
  },
  {
    "station": "Sham Shui Po",
    "temp_c": 29,
    "humidity_pct": 82,
    "wet_bulb_temp_c": 26.47,
    "composite_risk_score": 4.0,
    "risk_level": "Safe",
    "recorded_at": "2026-07-08T10:08:48.553734+00:00"
  },
  {
    "station": "Kai Tak Runway Park",
    "temp_c": 29,
    "humidity_pct": 82,
    "wet_bulb_temp_c": 26.47,
    "composite_risk_score": 4.0,
    "risk_level": "Safe",
    "recorded_at": "2026-07-08T10:08:48.553751+00:00"
  },
  {
    "station": "Yuen Long Park",
    "temp_c": 29,
    "humidity_pct": 82,
    "wet_bulb_temp_c": 26.47,
    "composite_risk_score": 4.0,
    "risk_level": "Safe",
    "recorded_at": "2026-07-08T10:08:48.553764+00:00"
  },
  {
    "station": "Tai Mei Tuk",
    "temp_c": 27,
    "humidity_pct": 82,
    "wet_bulb_temp_c": 24.57,
    "composite_risk_score": 4.0,
    "risk_level": "Safe",
    "recorded_at": "2026-07-08T10:08:48.553777+00:00"
  }
]